ptp_ipdata_extractor/__init__.py
ptp_ipdata_extractor/ip_extractor.py
ptp_ipdata_extractor-0.3.0.dist-info/LICENSE
ptp_ipdata_extractor-0.3.0.dist-info/METADATA
ptp_ipdata_extractor-0.3.0.dist-info/WHEEL
ptp_ipdata_extractor-0.3.0.dist-info/top_level.txt
ptp_ipdata_extractor-0.3.0.dist-info/RECORD
