Metadata-Version: 2.1
Name: ptp-ipdata-extractor
Version: 0.3.0
Summary: A package to query and extract IP data with Kerberos authentication from IBI DB.
Author-email: Tali Polonsky <tali.polonsky@intel.com>
License: MIT
Requires-Python: >=3.8
License-File: LICENSE
Requires-Dist: requests-kerberos>=0.12.0
Requires-Dist: pandas>=1.1.0
Requires-Dist: requests>=2.24.0
Requires-Dist: cryptography>=3.4.0
